{"cameraMode":{"drawMode":0,"name":"Shaded","section":"Shading Mode"},"sceneLighting":true,"audioPlay":false,"sceneViewState":{"m_AlwaysRefresh":false,"showFog":true,"showSkybox":true,"showFlares":true,"showImageEffects":true,"showParticleSystems":true,"showVisualEffectGraphs":true,"m_FxEnabled":true},"in2DMode":false,"pivot":{"x":7.995643138885498,"y":3.2819442749023439,"z":-6.680272579193115},"rotation":{"x":0.12013167887926102,"y":-0.051780153065919879,"z":0.006396076176315546,"w":0.9912912845611572},"size":0.08853182196617127,"orthographic":false}